one_instance/__init__.py
one_instance/admin.py
one_instance/apps.py
one_instance/models.py
one_instance/tests.py
one_instance/views.py
one_instance/templates/one_instance/change_form.html
one_instance/templates/one_instance/object_history.html
django_one_instance-0.0.4.dist-info/AUTHORS
django_one_instance-0.0.4.dist-info/LICENSE
django_one_instance-0.0.4.dist-info/METADATA
django_one_instance-0.0.4.dist-info/WHEEL
django_one_instance-0.0.4.dist-info/top_level.txt
django_one_instance-0.0.4.dist-info/RECORD
