Metadata-Version: 2.1
Name: django-one-instance
Version: 0.0.4
Summary: A Django app to enforce the use of only one instance for a given model.
Home-page: https://github.com/federicodabrunzo/django-one-instance
Author: "Fedele Federico D'Abrunzo"
Author-email: dabrunzofederico@gmail.com
License: BSD-3-Clause
Project-URL: Source Code, https://github.com/federicodabrunzo/django-one-instance
Classifier: Framework :: Django
Classifier: Framework :: Django :: 3.2
Classifier: Framework :: Django :: 4.0
Classifier: Framework :: Django :: 4.1
Classifier: Framework :: Django :: 4.2
Classifier: Intended Audience :: Developers
Classifier: License :: OSI Approved :: BSD License
Classifier: Operating System :: OS Independent
Classifier: Programming Language :: Python
Classifier: Programming Language :: Python :: 3.6
Classifier: Programming Language :: Python :: 3.7
Classifier: Programming Language :: Python :: 3.8
Classifier: Programming Language :: Python :: 3.9
Classifier: Programming Language :: Python :: 3.10
Classifier: Programming Language :: Python :: 3.11
Requires-Python: >=3.6
License-File: LICENSE
License-File: AUTHORS
Requires-Dist: Django >=3.2
